chidian/__init__.py
chidian/core.py
chidian/data_mapping.py
chidian/lexicon.py
chidian/mapper.py
chidian/partials.py
chidian/table.py
chidian/lib/__init__.py
chidian/lib/core_helpers.py
chidian/lib/data_mapping_helpers.py
chidian/lib/filter_parser.py
chidian/lib/get_dsl_parser.py
chidian/lib/parser.py
chidian/lib/select_parser.py
chidian/lib/dsl/filter.peg
chidian/lib/dsl/get.peg
chidian/lib/dsl/select.peg
chidian-0.1.4.dist-info/licenses/LICENSE
chidian-0.1.4.dist-info/METADATA
chidian-0.1.4.dist-info/WHEEL
chidian-0.1.4.dist-info/top_level.txt
chidian-0.1.4.dist-info/RECORD
