Metadata-Version: 2.4
Name: chidian
Version: 0.1.4
Classifier: Programming Language :: Python :: 3
Classifier: Programming Language :: Python :: 3.8
Classifier: Programming Language :: Python :: 3.9
Classifier: Programming Language :: Python :: 3.10
Classifier: Programming Language :: Python :: 3.11
Classifier: Programming Language :: Python :: 3.12
Classifier: Programming Language :: Python :: Implementation :: CPython
Classifier: Programming Language :: Python :: Implementation :: PyPy
Requires-Python: >=3.8
License-File: LICENSE
Requires-Dist: parsimonious>=0.10.0
Requires-Dist: pyarrow>=17.0.0
Requires-Dist: pydantic<3.0.0,>=2.10.6
Provides-Extra: pandas
Requires-Dist: pandas>=2.0; extra == "pandas"
Provides-Extra: polars
Requires-Dist: polars>=0.20; extra == "polars"
Provides-Extra: dfs
Requires-Dist: pandas>=2.0; extra == "dfs"
Requires-Dist: polars>=0.20; extra == "dfs"
Dynamic: license-file
